SAUIGeo/SAU.py
SAUIGeo/__init__.py
sauigeo-1.3.5.dist-info/METADATA
sauigeo-1.3.5.dist-info/WHEEL
sauigeo-1.3.5.dist-info/top_level.txt
sauigeo-1.3.5.dist-info/RECORD
